nanohubtools/__init__.py
nanohubtools/_version.py
nanohubtools/api.py
nanohubtools/crystalsimplified.py
nanohubtools/crystalviewer.py
nanohubtools/dftqe.py
nanohubtools/hubxml.py
nanohubtools/kronig_penney.py
nanohubtools/kronigsimplified.py
nanohubtools/nanohubtools.py
nanohubtools/plotlywidget.py
nanohubtools/pntoy.py
nanohubtools/pntoysimplified.py
nanohubtools/qdottools.py
nanohubtools/rappturetool.py
nanohubtools/semi.py
nanohubtools/assets/__init__.py
nanohubtools/assets/bravais1.png
nanohubtools/assets/bravais2.png
nanohubtools/assets/bravais3.png
nanohubtools/assets/bravais4.png
nanohubtools/assets/bravais5.png
nanohubtools/assets/bravais6.png
nanohubtools/assets/bravais7.png
nanohubtools/assets/crystal1.png
nanohubtools/assets/crystal10.png
nanohubtools/assets/crystal11.png
nanohubtools/assets/crystal12.png
nanohubtools/assets/crystal2.png
nanohubtools/assets/crystal3.png
nanohubtools/assets/crystal4.png
nanohubtools/assets/crystal5.png
nanohubtools/assets/crystal6.png
nanohubtools/assets/crystal7.png
nanohubtools/assets/crystal8.png
nanohubtools/assets/crystal9.png
nanohubtools/assets/pot_desc1.png
nanohubtools/assets/pot_desc10.png
nanohubtools/assets/pot_desc11.png
nanohubtools/assets/pot_desc2.png
nanohubtools/assets/pot_desc3.png
nanohubtools/assets/pot_desc4.png
nanohubtools/assets/pot_desc5.png
nanohubtools/assets/pot_desc6.png
nanohubtools/assets/pot_desc7.png
nanohubtools/assets/pot_desc8.png
nanohubtools/assets/pot_desc9.png
nanohubtools/assets/potential1.png
nanohubtools/assets/potential2.png
nanohubtools/assets/potential3.png
nanohubtools/assets/potential4.png
nanohubtools/assets/potential5.png
nanohubtools/assets/potential6.png
nanohubtools/assets/potential7.png
nanohubtools/assets/potential8.png
nanohubtools-0.2.3.data/data/assets/bravais1.png
nanohubtools-0.2.3.data/data/assets/bravais2.png
nanohubtools-0.2.3.data/data/assets/bravais3.png
nanohubtools-0.2.3.data/data/assets/bravais4.png
nanohubtools-0.2.3.data/data/assets/bravais5.png
nanohubtools-0.2.3.dist-info/METADATA
nanohubtools-0.2.3.dist-info/WHEEL
nanohubtools-0.2.3.dist-info/top_level.txt
nanohubtools-0.2.3.dist-info/RECORD
