Metadata-Version: 2.1
Name: nanohubtools
Version: 0.2.3
Summary: A set of tools to run nanoHubtools
Home-page: https://github.com/denphi/nanohubtools
Author: Project Jupyter contributor
Author-email: denphi@denphi.com
License: BSD
Keywords: Jupyter,Widgets,IPython
Platform: Linux
Platform: Mac OS X
Platform: Windows
Classifier: Intended Audience :: Developers
Classifier: Intended Audience :: Science/Research
Classifier: License :: OSI Approved :: BSD License
Classifier: Programming Language :: Python
Classifier: Programming Language :: Python :: 3
Classifier: Programming Language :: Python :: 3.4
Classifier: Programming Language :: Python :: 3.5
Classifier: Programming Language :: Python :: 3.6
Classifier: Framework :: Jupyter
Requires-Dist: floatview (>=0.1.11)
Requires-Dist: plotly (>=4.1.0)
Requires-Dist: numpy (>=1.16.0)
Requires-Dist: hublib (>=0.9.94)
Provides-Extra: docs
Provides-Extra: examples
Provides-Extra: test
